[
  {
    "title": "OCM",
    "description": "Just enough NSFW to make long playthroughs interesting.",
    "author": "BWAP",
    "maintainers": [
      "github/ArnoldDP"
    ],
    "game": "skyrimspecialedition",
    "official": false,
    "tags": [
      "OStim",
      "Seasons of Skyrim",
      "Simonrim",
      "BHUNP",
      "HIMBO",
      "Performance Profile"
    ],
    "nsfw": true,
    "utility_list": false,
    "image_contains_title": true,
    "DisplayVersionOnlyInInstallerView": false,
    "force_down": false,
    "links": {
      "image": "https://raw.githubusercontent.com/ArnoldDP/OStim-Community-Modlist/main/mli7.png",
      "readme": "https://github.com/ArnoldDP/OStim-Community-Modlist/blob/main/README.md",
      "download": "https://authored-files.wabbajack.org/OCM.wabbajack_d91aa7d3-978e-45c0-8afc-29b193b93660",
      "machineURL": "ostimisgood",
      "discordURL": "https://discord.gg/Wbq5mvKRrk"
    },
    "download_metadata": {
      "Hash": "7dpdKKn991U=",
      "Size": 2265328658,
      "NumberOfArchives": 1351,
      "SizeOfArchives": 164011695797,
      "NumberOfInstalledFiles": 340943,
      "SizeOfInstalledFiles": 293351840285
    },
    "version": "1.4.5",
    "dateCreated": "1970-01-01T00:00:00Z",
    "dateUpdated": "2024-03-24T20:50:42.2918142Z",
    "repositoryName": ""
  }
]
