[
  {
    "title": "OCM",
    "description": "Just enough NSFW to make long playthroughs interesting.",
    "author": "BWAP",
    "maintainers": [
      "github/ArnoldDP"
    ],
    "game": "skyrimspecialedition",
    "official": false,
    "tags": [
      "OStim",
      "Seasons of Skyrim",
      "Simonrim",
      "BHUNP",
      "HIMBO",
      "Vanilla\u002B",
      "Performance Profile"
    ],
    "nsfw": true,
    "utility_list": false,
    "image_contains_title": true,
    "DisplayVersionOnlyInInstallerView": false,
    "force_down": false,
    "links": {
      "image": "https://raw.githubusercontent.com/ArnoldDP/OStim-Community-Modlist/main/mli8.png",
      "readme": "https://github.com/ArnoldDP/OStim-Community-Modlist/blob/main/README.md",
      "download": "https://authored-files.wabbajack.org/OCM.wabbajack_a373c32e-6910-4e93-bac0-5baf43b4c912",
      "machineURL": "ostimisgood",
      "discordURL": "https://discord.gg/Wbq5mvKRrk"
    },
    "download_metadata": {
      "Hash": "7vaaXSeo5PU=",
      "Size": 974102402,
      "NumberOfArchives": 1368,
      "SizeOfArchives": 147755124246,
      "NumberOfInstalledFiles": 314194,
      "SizeOfInstalledFiles": 254414119749
    },
    "version": "1.5.4",
    "dateCreated": "1970-01-01T00:00:00Z",
    "dateUpdated": "2024-05-21T20:52:20.2678195Z",
    "repositoryName": ""
  }
]